algo/__init__.py
algo/base.py
backend/__init__.py
backend/backend.py
backend/kafka.py
backend/socket.py
broker/__init__.py
broker/connection.py
broker/ibkr/__init__.py
broker/ibkr/base.py
broker/ibkr/ibdata.py
broker/ibkr/ibstore.py
config/__init__.py
config/base.py
data/__init__.py
data/feed.py
data/feedHandler.py
data/dataset/__init__.py
data/dataset/base.py
data/dataset/features.py
data/live/__init__.py
data/live/ib_stream.py
data/live/producers/__init__.py
data/live/producers/ibkr_producer.py
data/live/producers/producer.py
data/storage/__init__.py
domain/__init__.py
domain/instrument/__init__.py
domain/instrument/core.py
model/__init__.py
strategy/__init__.py
tests/__init__.py
tests/ibkr_producer_test.py
utils/__init__.py
AlgoVision_Quant_Research-0.0.2.dist-info/LICENSE.txt
AlgoVision_Quant_Research-0.0.2.dist-info/METADATA
AlgoVision_Quant_Research-0.0.2.dist-info/WHEEL
AlgoVision_Quant_Research-0.0.2.dist-info/top_level.txt
AlgoVision_Quant_Research-0.0.2.dist-info/RECORD
