Metadata-Version: 2.1
Name: AlgoVision-Quant-Research
Version: 0.0.2
Summary: Library for AlgoVision's Trading Algorithm Development Environment
Author-email: Julian Wiley <julian@julianwiley.com>
Maintainer-email: Julian Wiley <julian@julianwiley.com>
License: Copyright (c) 2016 The Python Packaging Authority (PyPA)
Project-URL: Homepage, https://github.com/AlgoTech-Capital-Management/Quant-Research
Project-URL: Bug Reports, https://github.com/AlgoTech-Capital-Management/Quant-Research/issues
Project-URL: Source, https://github.com/AlgoTech-Capital-Management/Quant-Research
Keywords: sample,setuptools,development
Classifier: Development Status :: 3 - Alpha
Classifier: Intended Audience :: Developers
Classifier: Topic :: Software Development :: Build Tools
Classifier: License :: OSI Approved :: MIT License
Classifier: Programming Language :: Python :: 3
Classifier: Programming Language :: Python :: 3.7
Classifier: Programming Language :: Python :: 3.8
Classifier: Programming Language :: Python :: 3.9
Classifier: Programming Language :: Python :: 3.10
Classifier: Programming Language :: Python :: 3.11
Classifier: Programming Language :: Python :: 3 :: Only
Requires-Python: >=3.7
License-File: LICENSE.txt
Requires-Dist: peppercorn
Provides-Extra: dev
Requires-Dist: check-manifest ; extra == 'dev'
Provides-Extra: test
Requires-Dist: coverage ; extra == 'test'
